{
  "max_generations": 5,
  "husband": {
    "firstName": "Александр",
    "lastName": "Петров",
    "patronymic": "Иванович",
    "spouse": {
      "firstName": "Елена",
      "lastName": "Петрова",
      "patronymic": "Николаевна"
    },
    "children": [
      {
        "firstName": "Дмитрий",
        "lastName": "Петров",
        "patronymic": "Александрович",
        "spouse": {
          "firstName": "Ирина",
          "lastName": "Петрова",
          "patronymic": "Владимировна"
        },
        "children": [
          {
            "firstName": "Артём",
            "lastName": "Петров",
            "patronymic": "Дмитриевич",
            "spouse": {
              "firstName": "Анна",
              "lastName": "Петрова",
              "patronymic": "Сергеевна"
            },
            "children": [
              {
                "firstName": "Максим",
                "lastName": "Петров",
                "patronymic": "Артёмович",
                "spouse": {
                  "firstName": "Ольга",
                  "lastName": "Петрова",
                  "patronymic": "Алексеевна"
                },
                "children": [
                  {
                    "firstName": "Кирилл",
                    "lastName": "Петров",
                    "patronymic": "Максимович",
                    "spouse": null,
                    "children": []
                  },
                  {
                    "firstName": "Вероника",
                    "lastName": "Петрова",
                    "patronymic": "Максимовна",
                    "spouse": null,
                    "children": []
                  },
                  {
                    "firstName": "Даниил",
                    "lastName": "Петров",
                    "patronymic": "Максимович",
                    "spouse": null,
                    "children": []
                  },
                  {
                    "firstName": "Алиса",
                    "lastName": "Петрова",
                    "patronymic": "Максимовна",
                    "spouse": null,
                    "children": []
                  },
                  {
                    "firstName": "Тимофей",
                    "lastName": "Петров",
                    "patronymic": "Максимович",
                    "spouse": null,
                    "children": []
                  }
                ]
              },
              {
                "firstName": "Екатерина",
                "lastName": "Петрова",
                "patronymic": "Артёмовна",
                "spouse": {
                  "firstName": "Игорь",
                  "lastName": "Соколов",
                  "patronymic": "Павлович"
                },
                "children": [
                  {
                    "firstName": "Андрей",
                    "lastName": "Соколов",
                    "patronymic": "Игоревич",
                    "spouse": null,
                    "children": []
                  },
                  {
                    "firstName": "Мария",
                    "lastName": "Соколова",
                    "patronymic": "Игоревна",
                    "spouse": null,
                    "children": []
                  },
                  {
                    "firstName": "Денис",
                    "lastName": "Соколов",
                    "patronymic": "Игоревич",
                    "spouse": null,
                    "children": []
                  },
                  {
                    "firstName": "Полина",
                    "lastName": "Соколова",
                    "patronymic": "Игоревна",
                    "spouse": null,
                    "children": []
                  },
                  {
                    "firstName": "Егор",
                    "lastName": "Соколов",
                    "patronymic": "Игоревич",
                    "spouse": null,
                    "children": []
                  }
                ]
              },
              {
                "firstName": "Дарья",
                "lastName": "Петрова",
                "patronymic": "Артёмовна",
                "spouse": {
                  "firstName": "Михаил",
                  "lastName": "Волков",
                  "patronymic": "Андреевич"
                },
                "children": [
                  {
                    "firstName": "София",
                    "lastName": "Волкова",
                    "patronymic": "Михайловна",
                    "spouse": null,
                    "children": []
                  },
                  {
                    "firstName": "Иван",
                    "lastName": "Волков",
                    "patronymic": "Михайлович",
                    "spouse": null,
                    "children": []
                  },
                  {
                    "firstName": "Анастасия",
                    "lastName": "Волкова",
                    "patronymic": "Михайловна",
                    "spouse": null,
                    "children": []
                  },
                  {
                    "firstName": "Никита",
                    "lastName": "Волков",
                    "patronymic": "Михайлович",
                    "spouse": null,
                    "children": []
                  },
                  {
                    "firstName": "Валерия",
                    "lastName": "Волкова",
                    "patronymic": "Михайловна",
                    "spouse": null,
                    "children": []
                  }
                ]
              },
              {
                "firstName": "Роман",
                "lastName": "Петров",
                "patronymic": "Артёмович",
                "spouse": {
                  "firstName": "Юлия",
                  "lastName": "Петрова",
                  "patronymic": "Дмитриевна"
                },
                "children": [
                  {
                    "firstName": "Глеб",
                    "lastName": "Петров",
                    "patronymic": "Романович",
                    "spouse": null,
                    "children": []
                  },
                  {
                    "firstName": "Ангелина",
                    "lastName": "Петрова",
                    "patronymic": "Романовна",
                    "spouse": null,
                    "children": []
                  },
                  {
                    "firstName": "Матвей",
                    "lastName": "Петров",
                    "patronymic": "Романович",
                    "spouse": null,
                    "children": []
                  },
                  {
                    "firstName": "Ева",
                    "lastName": "Петрова",
                    "patronymic": "Романовна",
                    "spouse": null,
                    "children": []
                  },
                  {
                    "firstName": "Лев",
                    "lastName": "Петров",
                    "patronymic": "Романович",
                    "spouse": null,
                    "children": []
                  }
                ]
              },
              {
                "firstName": "Василиса",
                "lastName": "Петрова",
                "patronymic": "Артёмовна",
                "spouse": {
                  "firstName": "Алексей",
                  "lastName": "Морозов",
                  "patronymic": "Витальевич"
                },
                "children": [
                  {
                    "firstName": "Ксения",
                    "lastName": "Морозова",
                    "patronymic": "Алексеевна",
                    "spouse": null,
                    "children": []
                  },
                  {
                    "firstName": "Степан",
                    "lastName": "Морозов",
                    "patronymic": "Алексеевич",
                    "spouse": null,
                    "children": []
                  },
                  {
                    "firstName": "Арина",
                    "lastName": "Морозова",
                    "patronymic": "Алексеевна",
                    "spouse": null,
                    "children": []
                  },
                  {
                    "firstName": "Захар",
                    "lastName": "Морозов",
                    "patronymic": "Алексеевич",
                    "spouse": null,
                    "children": []
                  },
                  {
                    "firstName": "Мирослава",
                    "lastName": "Морозова",
                    "patronymic": "Алексеевна",
                    "spouse": null,
                    "children": []
                  }
                ]
              }
            ]
          },
          {
            "firstName": "Владислав",
            "lastName": "Петров",
            "patronymic": "Дмитриевич",
            "spouse": {
              "firstName": "Татьяна",
              "lastName": "Петрова",
              "patronymic": "Юрьевна"
            },
            "children": [
              {
                "firstName": "********** Александра **********",
                "lastName": "Петрова",
                "patronymic": "Владиславовна",
                "spouse": {
                    "firstName": "Татьяна",
                    "lastName": "Петрова",
                    "patronymic": "Юрьевна"
                  },
                "children": [
                  {
                    "firstName": "София",
                    "lastName": "Волкова",
                    "patronymic": "Михайловна",
                    "spouse": null,
                    "children": []
                  },
                  {
                    "firstName": "Иван",
                    "lastName": "Волков",
                    "patronymic": "Михайлович",
                    "spouse": null,
                    "children": []
                  },
                  {
                    "firstName": "Анастасия",
                    "lastName": "Волкова",
                    "patronymic": "Михайловна",
                    "spouse": null,
                    "children": []
                  },
                  {
                    "firstName": "Никита",
                    "lastName": "Волков",
                    "patronymic": "Михайлович",
                    "spouse": null,
                    "children": []
                  },
                  {
                    "firstName": "Валерия",
                    "lastName": "Волкова",
                    "patronymic": "Михайловна",
                    "spouse": null,
                    "children": []
                  }
                ]
              },
              {
                "firstName": "Константин",
                "lastName": "Петров",
                "patronymic": "Владиславович",
                "spouse": null,
                "children": [
                  {
                    "firstName": "София",
                    "lastName": "Волкова",
                    "patronymic": "Михайловна",
                    "spouse": null,
                    "children": []
                  },
                  {
                    "firstName": "Иван",
                    "lastName": "Волков",
                    "patronymic": "Михайлович",
                    "spouse": null,
                    "children": []
                  },
                  {
                    "firstName": "Анастасия",
                    "lastName": "Волкова",
                    "patronymic": "Михайловна",
                    "spouse": null,
                    "children": []
                  },
                  {
                    "firstName": "Никита",
                    "lastName": "Волков",
                    "patronymic": "Михайлович",
                    "spouse": null,
                    "children": []
                  },
                  {
                    "firstName": "Валерия",
                    "lastName": "Волкова",
                    "patronymic": "Михайловна",
                    "spouse": null,
                    "children": []
                  }
                ]
              },
              {
                "firstName": "Елизавета",
                "lastName": "Петрова",
                "patronymic": "Владиславовна",
                "spouse": null,
                "children": [
                  {
                    "firstName": "София",
                    "lastName": "Волкова",
                    "patronymic": "Михайловна",
                    "spouse": null,
                    "children": []
                  },
                  {
                    "firstName": "Иван",
                    "lastName": "Волков",
                    "patronymic": "Михайлович",
                    "spouse": null,
                    "children": []
                  },
                  {
                    "firstName": "Анастасия",
                    "lastName": "Волкова",
                    "patronymic": "Михайловна",
                    "spouse": null,
                    "children": []
                  },
                  {
                    "firstName": "Никита",
                    "lastName": "Волков",
                    "patronymic": "Михайлович",
                    "spouse": null,
                    "children": []
                  },
                  {
                    "firstName": "Валерия",
                    "lastName": "Волкова",
                    "patronymic": "Михайловна",
                    "spouse": null,
                    "children": []
                  }
                ]
              },
              {
                "firstName": "Ярослав",
                "lastName": "Петров",
                "patronymic": "Владиславович",
                "spouse": null,
                "children": [
                  {
                    "firstName": "София",
                    "lastName": "Волкова",
                    "patronymic": "Михайловна",
                    "spouse": null,
                    "children": []
                  },
                  {
                    "firstName": "Иван",
                    "lastName": "Волков",
                    "patronymic": "Михайлович",
                    "spouse": null,
                    "children": []
                  },
                  {
                    "firstName": "Анастасия",
                    "lastName": "Волкова",
                    "patronymic": "Михайловна",
                    "spouse": null,
                    "children": []
                  },
                  {
                    "firstName": "Никита",
                    "lastName": "Волков",
                    "patronymic": "Михайлович",
                    "spouse": null,
                    "children": []
                  },
                  {
                    "firstName": "Валерия",
                    "lastName": "Волкова",
                    "patronymic": "Михайловна",
                    "spouse": null,
                    "children": []
                  }
                ]
              },
              {
                "firstName": "Диана",
                "lastName": "Петрова",
                "patronymic": "Владиславовна",
                "spouse": null,
                "children": [
                  {
                    "firstName": "София",
                    "lastName": "Волкова",
                    "patronymic": "Михайловна",
                    "spouse": null,
                    "children": []
                  },
                  {
                    "firstName": "Иван",
                    "lastName": "Волков",
                    "patronymic": "Михайлович",
                    "spouse": null,
                    "children": []
                  },
                  {
                    "firstName": "Анастасия",
                    "lastName": "Волкова",
                    "patronymic": "Михайловна",
                    "spouse": null,
                    "children": []
                  },
                  {
                    "firstName": "Никита",
                    "lastName": "Волков",
                    "patronymic": "Михайлович",
                    "spouse": null,
                    "children": []
                  },
                  {
                    "firstName": "Валерия",
                    "lastName": "Волкова",
                    "patronymic": "Михайловна",
                    "spouse": null,
                    "children": []
                  }
                ]
              }
            ]
          },
          {
            "firstName": "Ольга",
            "lastName": "Петрова",
            "patronymic": "Дмитриевна",
            "spouse": {
              "firstName": "Николай",
              "lastName": "Козлов",
              "patronymic": "Александрович"
            },
            "children": [
              {
                "firstName": "Антон",
                "lastName": "Козлов",
                "patronymic": "Николаевич",
                "spouse": null,
                "children": [
                  {
                    "firstName": "Ксения",
                    "lastName": "Морозова",
                    "patronymic": "Алексеевна",
                    "spouse": null,
                    "children": []
                  },
                  {
                    "firstName": "Степан",
                    "lastName": "Морозов",
                    "patronymic": "Алексеевич",
                    "spouse": null,
                    "children": []
                  },
                  {
                    "firstName": "Арина",
                    "lastName": "Морозова",
                    "patronymic": "Алексеевна",
                    "spouse": null,
                    "children": []
                  },
                  {
                    "firstName": "Захар",
                    "lastName": "Морозов",
                    "patronymic": "Алексеевич",
                    "spouse": null,
                    "children": []
                  },
                  {
                    "firstName": "Мирослава",
                    "lastName": "Морозова",
                    "patronymic": "Алексеевна",
                    "spouse": null,
                    "children": []
                  }
                ]
              },
              {
                "firstName": "Виктория",
                "lastName": "Козлова",
                "patronymic": "Николаевна",
                "spouse": null,
                "children": [
                  
                ]
              },
              {
                "firstName": "Сергей",
                "lastName": "Козлов",
                "patronymic": "Николаевич",
                "spouse": null,
                "children": [
                  {
                    "firstName": "Ксения",
                    "lastName": "Морозова",
                    "patronymic": "Алексеевна",
                    "spouse": null,
                    "children": []
                  },
                  {
                    "firstName": "Степан",
                    "lastName": "Морозов",
                    "patronymic": "Алексеевич",
                    "spouse": null,
                    "children": []
                  },
                  {
                    "firstName": "Арина",
                    "lastName": "Морозова",
                    "patronymic": "Алексеевна",
                    "spouse": null,
                    "children": []
                  },
                  {
                    "firstName": "Захар",
                    "lastName": "Морозов",
                    "patronymic": "Алексеевич",
                    "spouse": null,
                    "children": []
                  },
                  {
                    "firstName": "Мирослава",
                    "lastName": "Морозова",
                    "patronymic": "Алексеевна",
                    "spouse": null,
                    "children": []
                  }
                ]
              },
              {
                "firstName": "Наталья",
                "lastName": "Козлова",
                "patronymic": "Николаевна",
                "spouse": null,
                "children": [
                  {
                    "firstName": "Ксения",
                    "lastName": "Морозова",
                    "patronymic": "Алексеевна",
                    "spouse": null,
                    "children": []
                  },
                  {
                    "firstName": "Степан",
                    "lastName": "Морозов",
                    "patronymic": "Алексеевич",
                    "spouse": null,
                    "children": []
                  },
                  {
                    "firstName": "Арина",
                    "lastName": "Морозова",
                    "patronymic": "Алексеевна",
                    "spouse": null,
                    "children": []
                  },
                  {
                    "firstName": "Захар",
                    "lastName": "Морозов",
                    "patronymic": "Алексеевич",
                    "spouse": null,
                    "children": []
                  },
                  {
                    "firstName": "Мирослава",
                    "lastName": "Морозова",
                    "patronymic": "Алексеевна",
                    "spouse": null,
                    "children": []
                  }
                ]
              },
              {
                "firstName": "Павел",
                "lastName": "Козлов",
                "patronymic": "Николаевич",
                "spouse": null,
                "children": [
                  {
                    "firstName": "Ксения",
                    "lastName": "Морозова",
                    "patronymic": "Алексеевна",
                    "spouse": null,
                    "children": []
                  },
                  {
                    "firstName": "Степан",
                    "lastName": "Морозов",
                    "patronymic": "Алексеевич",
                    "spouse": null,
                    "children": []
                  },
                  {
                    "firstName": "Арина",
                    "lastName": "Морозова",
                    "patronymic": "Алексеевна",
                    "spouse": null,
                    "children": []
                  },
                  {
                    "firstName": "Захар",
                    "lastName": "Морозов",
                    "patronymic": "Алексеевич",
                    "spouse": null,
                    "children": []
                  },
                  {
                    "firstName": "Мирослава",
                    "lastName": "Морозова",
                    "patronymic": "Алексеевна",
                    "spouse": null,
                    "children": []
                  }
                ]
              }
            ]
          },
          {
            "firstName": "Елена",
            "lastName": "Петрова",
            "patronymic": "Дмитриевна",
            "spouse": {
              "firstName": "Виктор",
              "lastName": "Новиков",
              "patronymic": "Романович"
            },
            "children": [
              {
                "firstName": "Денис",
                "lastName": "Новиков",
                "patronymic": "Викторович",
                "spouse": null,
                "children": []
              },
              {
                "firstName": "Юлия",
                "lastName": "Новикова",
                "patronymic": "Викторовна",
                "spouse": null,
                "children": []
              },
              {
                "firstName": "Арсений",
                "lastName": "Новиков",
                "patronymic": "Викторович",
                "spouse": null,
                "children": []
              },
              {
                "firstName": "Кристина",
                "lastName": "Новикова",
                "patronymic": "Викторовна",
                "spouse": null,
                "children": []
              },
              {
                "firstName": "Марк",
                "lastName": "Новиков",
                "patronymic": "Викторович",
                "spouse": null,
                "children": []
              }
            ]
          },
          {
            "firstName": "Игорь",
            "lastName": "Петров",
            "patronymic": "Дмитриевич",
            "spouse": {
              "firstName": "Светлана",
              "lastName": "Петрова",
              "patronymic": "Анатольевна"
            },
            "children": [
              {
                "firstName": "Алиса",
                "lastName": "Петрова",
                "patronymic": "Игоревна",
                "spouse": null,
                "children": []
              },
              {
                "firstName": "Артур",
                "lastName": "Петров",
                "patronymic": "Игоревич",
                "spouse": null,
                "children": []
              },
              {
                "firstName": "Марьяна",
                "lastName": "Петрова",
                "patronymic": "Игоревна",
                "spouse": null,
                "children": []
              },
              {
                "firstName": "Богдан",
                "lastName": "Петров",
                "patronymic": "Игоревич",
                "spouse": null,
                "children": []
              },
              {
                "firstName": "Эмилия",
                "lastName": "Петрова",
                "patronymic": "Игоревна",
                "spouse": null,
                "children": []
              }
            ]
          }
        ]
      },
      {
        "firstName": "Анна",
        "lastName": "Петрова",
        "patronymic": "Александровна",
        "spouse": {
          "firstName": "Сергей",
          "lastName": "Михайлов",
          "patronymic": "Петрович"
        },
        "children": [
          {
            "firstName": "Максим",
            "lastName": "Михайлов",
            "patronymic": "Сергеевич",
            "spouse": {
              "firstName": "Екатерина",
              "lastName": "Михайлова",
              "patronymic": "Андреевна"
            },
            "children": [
              {
                "firstName": "Артём",
                "lastName": "Михайлов",
                "patronymic": "Максимович",
                "spouse": null,
                "children": []
              },
              {
                "firstName": "София",
                "lastName": "Михайлова",
                "patronymic": "Максимовна",
                "spouse": null,
                "children": []
              },
              {
                "firstName": "Дмитрий",
                "lastName": "Михайлов",
                "patronymic": "Максимович",
                "spouse": null,
                "children": []
              },
              {
                "firstName": "Анна",
                "lastName": "Михайлова",
                "patronymic": "Максимовна",
                "spouse": null,
                "children": []
              },
              {
                "firstName": "Иван",
                "lastName": "Михайлов",
                "patronymic": "Максимович",
                "spouse": null,
                "children": []
              }
            ]
          },
          {
            "firstName": "Дарья",
            "lastName": "Михайлова",
            "patronymic": "Сергеевна",
            "spouse": {
              "firstName": "Алексей",
              "lastName": "Смирнов",
              "patronymic": "Николаевич"
            },
            "children": [
              {
                "firstName": "Николай",
                "lastName": "Смирнов",
                "patronymic": "Алексеевич",
                "spouse": null,
                "children": []
              },
              {
                "firstName": "Елена",
                "lastName": "Смирнова",
                "patronymic": "Алексеевна",
                "spouse": null,
                "children": []
              },
              {
                "firstName": "Павел",
                "lastName": "Смирнов",
                "patronymic": "Алексеевич",
                "spouse": null,
                "children": []
              },
              {
                "firstName": "Ольга",
                "lastName": "Смирнова",
                "patronymic": "Алексеевна",
                "spouse": null,
                "children": []
              },
              {
                "firstName": "Сергей",
                "lastName": "Смирнов",
                "patronymic": "Алексеевич",
                "spouse": null,
                "children": []
              }
            ]
          },
          {
            "firstName": "Никита",
            "lastName": "Михайлов",
            "patronymic": "Сергеевич",
            "spouse": {
              "firstName": "Мария",
              "lastName": "Михайлова",
              "patronymic": "Игоревна"
            },
            "children": [
              {
                "firstName": "Андрей",
                "lastName": "Михайлов",
                "patronymic": "Никитич",
                "spouse": null,
                "children": []
              },
              {
                "firstName": "Анастасия",
                "lastName": "Михайлова",
                "patronymic": "Никитична",
                "spouse": null,
                "children": []
              },
              {
                "firstName": "Владимир",
                "lastName": "Михайлов",
                "patronymic": "Никитич",
                "spouse": null,
                "children": []
              },
              {
                "firstName": "Татьяна",
                "lastName": "Михайлова",
                "patronymic": "Никитична",
                "spouse": null,
                "children": []
              },
              {
                "firstName": "Юрий",
                "lastName": "Михайлов",
                "patronymic": "Никитич",
                "spouse": null,
                "children": []
              }
            ]
          },
          {
            "firstName": "Полина",
            "lastName": "Михайлова",
            "patronymic": "Сергеевна",
            "spouse": {
              "firstName": "Константин",
              "lastName": "Белов",
              "patronymic": "Дмитриевич"
            },
            "children": [
              {
                "firstName": "Михаил",
                "lastName": "Белов",
                "patronymic": "Константинович",
                "spouse": null,
                "children": []
              },
              {
                "firstName": "Евгения",
                "lastName": "Белова",
                "patronymic": "Константиновна",
                "spouse": null,
                "children": []
              },
              {
                "firstName": "Александр",
                "lastName": "Белов",
                "patronymic": "Константинович",
                "spouse": null,
                "children": []
              },
              {
                "firstName": "Ксения",
                "lastName": "Белова",
                "patronymic": "Константиновна",
                "spouse": null,
                "children": []
              },
              {
                "firstName": "Роман",
                "lastName": "Белов",
                "patronymic": "Константинович",
                "spouse": null,
                "children": []
              }
            ]
          },
          {
            "firstName": "Егор",
            "lastName": "Михайлов",
            "patronymic": "Сергеевич",
            "spouse": {
              "firstName": "Алина",
              "lastName": "Михайлова",
              "patronymic": "Владимировна"
            },
            "children": [
              {
                "firstName": "Матвей",
                "lastName": "Михайлов",
                "patronymic": "Егорович",
                "spouse": null,
                "children": []
              },
              {
                "firstName": "Диана",
                "lastName": "Михайлова",
                "patronymic": "Егоровна",
                "spouse": null,
                "children": []
              },
              {
                "firstName": "Кирилл",
                "lastName": "Михайлов",
                "patronymic": "Егорович",
                "spouse": null,
                "children": []
              },
              {
                "firstName": "Милана",
                "lastName": "Михайлова",
                "patronymic": "Егоровна",
                "spouse": null,
                "children": []
              },
              {
                "firstName": "Арсений",
                "lastName": "Михайлов",
                "patronymic": "Егорович",
                "spouse": null,
                "children": []
              }
            ]
          }
        ]
      },
      {
        "firstName": "Екатерина",
        "lastName": "Петрова",
        "patronymic": "Александровна",
        "spouse": {
          "firstName": "Андрей",
          "lastName": "Фёдоров",
          "patronymic": "Владимирович"
        },
        "children": [
          {
            "firstName": "Тимофей",
            "lastName": "Фёдоров",
            "patronymic": "Андреевич",
            "spouse": {
              "firstName": "Наталья",
              "lastName": "Фёдорова",
              "patronymic": "Павловна"
            },
            "children": [
              {
                "firstName": "Василий",
                "lastName": "Фёдоров",
                "patronymic": "Тимофеевич",
                "spouse": null,
                "children": []
              },
              {
                "firstName": "Мария",
                "lastName": "Фёдорова",
                "patronymic": "Тимофеевна",
                "spouse": null,
                "children": []
              },
              {
                "firstName": "Даниил",
                "lastName": "Фёдоров",
                "patronymic": "Тимофеевич",
                "spouse": null,
                "children": []
              },
              {
                "firstName": "Анастасия",
                "lastName": "Фёдорова",
                "patronymic": "Тимофеевна",
                "spouse": null,
                "children": []
              },
              {
                "firstName": "Максим",
                "lastName": "Фёдоров",
                "patronymic": "Тимофеевич",
                "spouse": null,
                "children": []
              }
            ]
          },
          {
            "firstName": "Варвара",
            "lastName": "Фёдорова",
            "patronymic": "Андреевна",
            "spouse": {
              "firstName": "Георгий",
              "lastName": "Соловьёв",
              "patronymic": "Петрович"
            },
            "children": [
              {
                "firstName": "Антон",
                "lastName": "Соловьёв",
                "patronymic": "Георгиевич",
                "spouse": null,
                "children": []
              },
              {
                "firstName": "Елизавета",
                "lastName": "Соловьёва",
                "patronymic": "Георгиевна",
                "spouse": null,
                "children": []
              },
              {
                "firstName": "Никита",
                "lastName": "Соловьёв",
                "patronymic": "Георгиевич",
                "spouse": null,
                "children": []
              },
              {
                "firstName": "София",
                "lastName": "Соловьёва",
                "patronymic": "Георгиевна",
                "spouse": null,
                "children": []
              },
              {
                "firstName": "Илья",
                "lastName": "Соловьёв",
                "patronymic": "Георгиевич",
                "spouse": null,
                "children": []
              }
            ]
          },
          {
            "firstName": "Лев",
            "lastName": "Фёдоров",
            "patronymic": "Андреевич",
            "spouse": {
              "firstName": "Вероника",
              "lastName": "Фёдорова",
              "patronymic": "Сергеевна"
            },
            "children": [
              {
                "firstName": "Степан",
                "lastName": "Фёдоров",
                "patronymic": "Львович",
                "spouse": null,
                "children": []
              },
              {
                "firstName": "Александра",
                "lastName": "Фёдорова",
                "patronymic": "Львовна",
                "spouse": null,
                "children": []
              },
              {
                "firstName": "Игорь",
                "lastName": "Фёдоров",
                "patronymic": "Львович",
                "spouse": null,
                "children": []
              },
              {
                "firstName": "Ева",
                "lastName": "Фёдорова",
                "patronymic": "Львовна",
                "spouse": null,
                "children": []
              },
              {
                "firstName": "Богдан",
                "lastName": "Фёдоров",
                "patronymic": "Львович",
                "spouse": null,
                "children": []
              }
            ]
          },
          {
            "firstName": "Ева",
            "lastName": "Фёдорова",
            "patronymic": "Андреевна",
            "spouse": {
              "firstName": "Владислав",
              "lastName": "Кузнецов",
              "patronymic": "Александрович"
            },
            "children": [
              {
                "firstName": "Алиса",
                "lastName": "Кузнецова",
                "patronymic": "Владиславовна",
                "spouse": null,
                "children": []
              },
              {
                "firstName": "Тимур",
                "lastName": "Кузнецов",
                "patronymic": "Владиславович",
                "spouse": null,
                "children": []
              },
              {
                "firstName": "Мирослава",
                "lastName": "Кузнецова",
                "patronymic": "Владиславовна",
                "spouse": null,
                "children": []
              },
              {
                "firstName": "Платон",
                "lastName": "Кузнецов",
                "patronymic": "Владиславович",
                "spouse": null,
                "children": []
              },
              {
                "firstName": "Майя",
                "lastName": "Кузнецова",
                "patronymic": "Владиславовна",
                "spouse": null,
                "children": []
              }
            ]
          },
          {
            "firstName": "Матвей",
            "lastName": "Фёдоров",
            "patronymic": "Андреевич",
            "spouse": {
              "firstName": "Полина",
              "lastName": "Фёдорова",
              "patronymic": "Александровна"
            },
            "children": [
              {
                "firstName": "Глеб",
                "lastName": "Фёдоров",
                "patronymic": "Матвеевич",
                "spouse": null,
                "children": []
              },
              {
                "firstName": "Злата",
                "lastName": "Фёдорова",
                "patronymic": "Матвеевна",
                "spouse": null,
                "children": []
              },
              {
                "firstName": "Артур",
                "lastName": "Фёдоров",
                "patronymic": "Матвеевич",
                "spouse": null,
                "children": []
              },
              {
                "firstName": "Кристина",
                "lastName": "Фёдорова",
                "patronymic": "Матвеевна",
                "spouse": null,
                "children": []
              },
              {
                "firstName": "Егор",
                "lastName": "Фёдоров",
                "patronymic": "Матвеевич",
                "spouse": null,
                "children": []
              }
            ]
          }
        ]
      },
      {
        "firstName": "Михаил",
        "lastName": "Петров",
        "patronymic": "Александрович",
        "spouse": {
          "firstName": "Наталья",
          "lastName": "Петрова",
          "patronymic": "Григорьевна"
        },
        "children": [
          {
            "firstName": "Георгий",
            "lastName": "Петров",
            "patronymic": "Михайлович",
            "spouse": {
              "firstName": "Татьяна",
              "lastName": "Петрова",
              "patronymic": "Ивановна"
            },
            "children": [
              {
                "firstName": "Андрей",
                "lastName": "Петров",
                "patronymic": "Георгиевич",
                "spouse": null,
                "children": []
              },
              {
                "firstName": "Виктория",
                "lastName": "Петрова",
                "patronymic": "Георгиевна",
                "spouse": null,
                "children": []
              },
              {
                "firstName": "Николай",
                "lastName": "Петров",
                "patronymic": "Георгиевич",
                "spouse": null,
                "children": []
              },
              {
                "firstName": "Екатерина",
                "lastName": "Петрова",
                "patronymic": "Георгиевна",
                "spouse": null,
                "children": []
              },
              {
                "firstName": "Павел",
                "lastName": "Петров",
                "patronymic": "Георгиевич",
                "spouse": null,
                "children": []
              }
            ]
          },
          {
            "firstName": "София",
            "lastName": "Петрова",
            "patronymic": "Михайловна",
            "spouse": {
              "firstName": "Илья",
              "lastName": "Козлов",
              "patronymic": "Анатольевич"
            },
            "children": [
              {
                "firstName": "Денис",
                "lastName": "Козлов",
                "patronymic": "Ильич",
                "spouse": null,
                "children": []
              },
              {
                "firstName": "Варвара",
                "lastName": "Козлова",
                "patronymic": "Ильинична",
                "spouse": null,
                "children": []
              },
              {
                "firstName": "Алексей",
                "lastName": "Козлов",
                "patronymic": "Ильич",
                "spouse": null,
                "children": []
              },
              {
                "firstName": "Мария",
                "lastName": "Козлова",
                "patronymic": "Ильинична",
                "spouse": null,
                "children": []
              },
              {
                "firstName": "Сергей",
                "lastName": "Козлов",
                "patronymic": "Ильич",
                "spouse": null,
                "children": []
              }
            ]
          },
          {
            "firstName": "Даниил",
            "lastName": "Петров",
            "patronymic": "Михайлович",
            "spouse": {
              "firstName": "Анна",
              "lastName": "Петрова",
              "patronymic": "Дмитриевна"
            },
            "children": [
              {
                "firstName": "Лев",
                "lastName": "Петров",
                "patronymic": "Даниилович",
                "spouse": null,
                "children": []
              },
              {
                "firstName": "Елена",
                "lastName": "Петрова",
                "patronymic": "Данииловна",
                "spouse": null,
                "children": []
              },
              {
                "firstName": "Артём",
                "lastName": "Петров",
                "patronymic": "Даниилович",
                "spouse": null,
                "children": []
              },
              {
                "firstName": "Ольга",
                "lastName": "Петрова",
                "patronymic": "Данииловна",
                "spouse": null,
                "children": []
              },
              {
                "firstName": "Максим",
                "lastName": "Петров",
                "patronymic": "Даниилович",
                "spouse": null,
                "children": []
              }
            ]
          },
          {
            "firstName": "Алиса",
            "lastName": "Петрова",
            "patronymic": "Михайловна",
            "spouse": {
              "firstName": "Дмитрий",
              "lastName": "Волков",
              "patronymic": "Сергеевич"
            },
            "children": [
              {
                "firstName": "Егор",
                "lastName": "Волков",
                "patronymic": "Дмитриевич",
                "spouse": null,
                "children": []
              },
              {
                "firstName": "Ксения",
                "lastName": "Волкова",
                "patronymic": "Дмитриевна",
                "spouse": null,
                "children": []
              },
              {
                "firstName": "Михаил",
                "lastName": "Волков",
                "patronymic": "Дмитриевич",
                "spouse": null,
                "children": []
              },
              {
                "firstName": "Анастасия",
                "lastName": "Волкова",
                "patronymic": "Дмитриевна",
                "spouse": null,
                "children": []
              },
              {
                "firstName": "Кирилл",
                "lastName": "Волков",
                "patronymic": "Дмитриевич",
                "spouse": null,
                "children": []
              }
            ]
          },
          {
            "firstName": "Роман",
            "lastName": "Петров",
            "patronymic": "Михайлович",
            "spouse": {
              "firstName": "Юлия",
              "lastName": "Петрова",
              "patronymic": "Константиновна"
            },
            "children": [
              {
                "firstName": "Иван",
                "lastName": "Петров",
                "patronymic": "Романович",
                "spouse": null,
                "children": []
              },
              {
                "firstName": "София",
                "lastName": "Петрова",
                "patronymic": "Романовна",
                "spouse": null,
                "children": []
              },
              {
                "firstName": "Александр",
                "lastName": "Петров",
                "patronymic": "Романович",
                "spouse": null,
                "children": []
              },
              {
                "firstName": "Мария",
                "lastName": "Петрова",
                "patronymic": "Романовна",
                "spouse": null,
                "children": []
              }
            ]
          }
        ]
      },
      {
        "firstName": "Татьяна",
        "lastName": "Петрова",
        "patronymic": "Александровна",
        "spouse": {
          "firstName": "Денис",
          "lastName": "Егоров",
          "patronymic": "Ильич"
        },
        "children": [
          {
            "firstName": "Илья",
            "lastName": "Егоров",
            "patronymic": "Денисович",
            "spouse": {
              "firstName": "Анастасия",
              "lastName": "Егорова",
              "patronymic": "Владимировна"
            },
            "children": [
              {
                "firstName": "Максим",
                "lastName": "Егоров",
                "patronymic": "Ильич",
                "spouse": null,
                "children": []
              },
              {
                "firstName": "Екатерина",
                "lastName": "Егорова",
                "patronymic": "Ильинична",
                "spouse": null,
                "children": []
              },
              {
                "firstName": "Дмитрий",
                "lastName": "Егоров",
                "patronymic": "Ильич",
                "spouse": null,
                "children": []
              },
              {
                "firstName": "Анна",
                "lastName": "Егорова",
                "patronymic": "Ильинична",
                "spouse": null,
                "children": []
              },
              {
                "firstName": "Артём",
                "lastName": "Егоров",
                "patronymic": "Ильич",
                "spouse": null,
                "children": []
              }
            ]
          },
          {
            "firstName": "Майя",
            "lastName": "Егорова",
            "patronymic": "Денисовна",
            "spouse": {
              "firstName": "Алексей",
              "lastName": "Соколов",
              "patronymic": "Васильевич"
            },
            "children": [
              {
                "firstName": "Сергей",
                "lastName": "Соколов",
                "patronymic": "Алексеевич",
                "spouse": null,
                "children": []
              },
              {
                "firstName": "Ольга",
                "lastName": "Соколова",
                "patronymic": "Алексеевна",
                "spouse": null,
                "children": []
              },
              {
                "firstName": "Николай",
                "lastName": "Соколов",
                "patronymic": "Алексеевич",
                "spouse": null,
                "children": []
              },
              {
                "firstName": "Татьяна",
                "lastName": "Соколова",
                "patronymic": "Алексеевна",
                "spouse": null,
                "children": []
              },
              {
                "firstName": "Андрей",
                "lastName": "Соколов",
                "patronymic": "Алексеевич",
                "spouse": null,
                "children": []
              }
            ]
          },
          {
            "firstName": "Артём",
            "lastName": "Егоров",
            "patronymic": "Денисович",
            "spouse": {
              "firstName": "Елена",
              "lastName": "Егорова",
              "patronymic": "Павловна"
            },
            "children": [
              {
                "firstName": "Павел",
                "lastName": "Егоров",
                "patronymic": "Артёмович",
                "spouse": null,
                "children": []
              },
              {
                "firstName": "Алиса",
                "lastName": "Егорова",
                "patronymic": "Артёмовна",
                "spouse": null,
                "children": []
              },
              {
                "firstName": "Роман",
                "lastName": "Егоров",
                "patronymic": "Артёмович",
                "spouse": null,
                "children": []
              },
              {
                "firstName": "Ксения",
                "lastName": "Егорова",
                "patronymic": "Артёмовна",
                "spouse": null,
                "children": []
              },
              {
                "firstName": "Михаил",
                "lastName": "Егоров",
                "patronymic": "Артёмович",
                "spouse": null,
                "children": []
              }
            ]
          },
          {
            "firstName": "Милана",
            "lastName": "Егорова",
            "patronymic": "Денисовна",
            "spouse": {
              "firstName": "Максим",
              "lastName": "Лебедев",
              "patronymic": "Игоревич"
            },
            "children": [
              {
                "firstName": "Никита",
                "lastName": "Лебедев",
                "patronymic": "Максимович",
                "spouse": null,
                "children": []
              },
              {
                "firstName": "София",
                "lastName": "Лебедева",
                "patronymic": "Максимовна",
                "spouse": null,
                "children": []
              },
              {
                "firstName": "Иван",
                "lastName": "Лебедев",
                "patronymic": "Максимович",
                "spouse": null,
                "children": []
              },
              {
                "firstName": "Мария",
                "lastName": "Лебедева",
                "patronymic": "Максимовна",
                "spouse": null,
                "children": []
              },
              {
                "firstName": "Даниил",
                "lastName": "Лебедев",
                "patronymic": "Максимович",
                "spouse": null,
                "children": []
              }
            ]
          },
          {
            "firstName": "Кирилл",
            "lastName": "Егоров",
            "patronymic": "Денисович",
            "spouse": {
              "firstName": "Валерия",
              "lastName": "Егорова",
              "patronymic": "Андреевна"
            },
            "children": [
              {
                "firstName": "Евгений",
                "lastName": "Егоров",
                "patronymic": "Кириллович",
                "spouse": null,
                "children": []
              },
              {
                "firstName": "Полина",
                "lastName": "Егорова",
                "patronymic": "Кирилловна",
                "spouse": null,
                "children": []
              },
              {
                "firstName": "Александра",
                "lastName": "Егорова",
                "patronymic": "Кирилловна",
                "spouse": null,
                "children": []
              },
              {
                "firstName": "Владимир",
                "lastName": "Егоров",
                "patronymic": "Кириллович",
                "spouse": null,
                "children": []
              },
              {
                "firstName": "Анастасия",
                "lastName": "Егорова",
                "patronymic": "Кирилловна",
                "spouse": null,
                "children": []
              }
            ]
          }
        ]
      }
    ]
  }
}